datasette_test/__init__.py
datasette_test-0.3.2.dist-info/LICENSE
datasette_test-0.3.2.dist-info/METADATA
datasette_test-0.3.2.dist-info/WHEEL
datasette_test-0.3.2.dist-info/top_level.txt
datasette_test-0.3.2.dist-info/RECORD
