Metadata-Version: 2.1
Name: datasette-test
Version: 0.3.2
Summary: Utilities to help write tests for Datasette plugins and applications
Author: Datasette
License: Apache-2.0
Project-URL: Homepage, https://github.com/datasette/datasette-test
Project-URL: Changelog, https://github.com/datasette/datasette-test/releases
Project-URL: Issues, https://github.com/datasette/datasette-test/issues
Project-URL: CI, https://github.com/datasette/datasette-test/actions
Classifier: License :: OSI Approved :: Apache Software License
Requires-Python: >=3.8
License-File: LICENSE
Requires-Dist: datasette
Requires-Dist: httpx
Requires-Dist: packaging
Requires-Dist: datasette-test-plugin
Provides-Extra: test
Requires-Dist: pytest ; extra == 'test'
Requires-Dist: pytest-asyncio ; extra == 'test'
